valoff_ie_api/__init__.py
valoff_ie_api/categories.json
valoff_ie_api/download.py
valoff_ie_api/local_authorities.json
valoff_ie_api/tests/test_download.py
valoff_ie_api-0.1.0.dist-info/LICENSE
valoff_ie_api-0.1.0.dist-info/WHEEL
valoff_ie_api-0.1.0.dist-info/METADATA
valoff_ie_api-0.1.0.dist-info/RECORD
