Metadata-Version: 2.1
Name: valoff-ie-api
Version: 0.1.0
Summary: An unofficial Python API for the Valuation Office REST API
License: MIT
Author: Rowan Molony
Author-email: rowan.molony@codema.ie
Requires-Python: >=3.6.1,<4.0
Classifier: License :: OSI Approved :: MIT License
Classifier: Programming Language :: Python :: 3
Classifier: Programming Language :: Python :: 3.10
Classifier: Programming Language :: Python :: 3.7
Classifier: Programming Language :: Python :: 3.8
Classifier: Programming Language :: Python :: 3.9
Requires-Dist: icontract (>=2.5.0,<3.0.0)
Requires-Dist: loguru (>=0.5.3,<0.6.0)
